temsomap/Mapper.py
temsomap/__init__.py
temsomap/_version_.py
temsomap/temso_utils.py
temsomap/treebuild.py
temsomap/utils.py
TemSOMap-0.0.3.dist-info/LICENSE
TemSOMap-0.0.3.dist-info/METADATA
TemSOMap-0.0.3.dist-info/WHEEL
TemSOMap-0.0.3.dist-info/top_level.txt
TemSOMap-0.0.3.dist-info/RECORD
