Metadata-Version: 2.1
Name: TemSOMap
Version: 0.0.3
Summary: Temporal-Spatial-Omics Mapping of single cells.
Home-page: 
Author: Xinhai Pan
Author-email: xpan78@gatech.edu
Classifier: Programming Language :: Python :: 3.11
Classifier: Operating System :: Unix
Requires-Python: >=3.8.5
License-File: LICENSE
Requires-Dist: pip
Requires-Dist: torch
Requires-Dist: pandas
Requires-Dist: numpy
Requires-Dist: scipy
Requires-Dist: matplotlib
Requires-Dist: seaborn
Requires-Dist: scanpy
Requires-Dist: scikit-learn
Requires-Dist: tqdm
